tg_hammer-0.0.3.dist-info/WHEEL
tg_hammer-0.0.3.dist-info/top_level.txt
tg_hammer-0.0.3.dist-info/METADATA
tg_hammer-0.0.3.dist-info/RECORD
tg_hammer-0.0.3.dist-info/metadata.json
tg_hammer-0.0.3.dist-info/DESCRIPTION.rst
hammer/__init__.py
hammer/vcs/base.py
hammer/vcs/hg.py
hammer/vcs/git.py
hammer/vcs/__init__.py
hammer/vcs/manager.py
