Metadata-Version: 2.0
Name: tg-hammer
Version: 0.0.3
Summary: Helpers for fabric based deployments.
Home-page: https://github.com/thorgate/tg-hammer
Author: Thorgate
Author-email: hi@thorgate.eu
License: BSD
Keywords: tg-hammer hammer fabric vcs git hg
Platform: UNKNOWN
Classifier: Development Status :: 2 - Pre-Alpha
Classifier: Intended Audience :: Developers
Classifier: License :: OSI Approved :: BSD License
Classifier: Natural Language :: English
Classifier: Programming Language :: Python :: 2
Requires-Dist: fabric (>=1.10.2,<2)
